simpnmr/__init__.py
simpnmr/__version__.py
simpnmr/config/__init__.py
simpnmr/config/config.py
simpnmr/tools/__init__.py
simpnmr/tools/batch_hf_plot.py
simpnmr/tools/batch_susc_plot.py
simpnmr/tools/plot_functional_dependence.py
simpnmr/tools/plot_susc_dependence.py
simpnmr/tools/coords_tools/__init__.py
simpnmr/tools/coords_tools/chemcraft_xyz.py
simpnmr/tools/coords_tools/transform.py
simpnmr/tools/coords_tools/xyz_format.py
simpnmr-1.3.0.dist-info/licenses/LICENSE
simpnmr-1.3.0.dist-info/METADATA
simpnmr-1.3.0.dist-info/WHEEL
simpnmr-1.3.0.dist-info/entry_points.txt
simpnmr-1.3.0.dist-info/top_level.txt
simpnmr-1.3.0.dist-info/RECORD
