Metadata-Version: 2.4
Name: simpnmr
Version: 1.3.0
Summary: A package for working with paramagnetic NMR spectra
Home-page: https://gitlab.com/suturina-group/simpnmr
Author: Suturina Group
Author-email: 
Classifier: Programming Language :: Python :: 3
Classifier: License :: OSI Approved :: GNU General Public License v3 (GPLv3)
Classifier: Operating System :: OS Independent
Requires-Python: >=3.10
License-File: LICENSE
Requires-Dist: numpy
Requires-Dist: scipy
Requires-Dist: sympy
Requires-Dist: matplotlib
Requires-Dist: pandas
Requires-Dist: pathos
Requires-Dist: pyyaml
Requires-Dist: pyyaml-include
Requires-Dist: adjustText
Provides-Extra: dev
Requires-Dist: pytest>=8.0; extra == "dev"
Dynamic: author
Dynamic: classifier
Dynamic: home-page
Dynamic: license-file
Dynamic: provides-extra
Dynamic: requires-dist
Dynamic: requires-python
Dynamic: summary
